LICENSE
colo/colo.py
colo/profiler.py
colo-1.1.1.dist-info/entry_points.txt
colo-1.1.1.dist-info/LICENSE
colo-1.1.1.dist-info/WHEEL
colo-1.1.1.dist-info/METADATA
colo-1.1.1.dist-info/RECORD
