Metadata-Version: 2.1
Name: colo
Version: 1.1.1
Summary: A simple script to print out the 256 terminal colors in various formats
Home-page: https://github.com/terminaldweller/colo
License: GPL3
Keywords: terminal,color
Author: terminaldweller
Author-email: thabogre@gmail.com
Requires-Python: >=3.8,<4.0
Classifier: Environment :: Console
Classifier: License :: Other/Proprietary License
Classifier: Programming Language :: Python :: 3
Classifier: Programming Language :: Python :: 3.10
Classifier: Programming Language :: Python :: 3.8
Classifier: Programming Language :: Python :: 3.9
Project-URL: Repository, https://github.com/terminaldweller/colo
